odoo/addons/mass_mailing_unique/README.rst
odoo/addons/mass_mailing_unique/__init__.py
odoo/addons/mass_mailing_unique/__manifest__.py
odoo/addons/mass_mailing_unique/hooks.py
odoo/addons/mass_mailing_unique/i18n/ca.po
odoo/addons/mass_mailing_unique/i18n/de.po
odoo/addons/mass_mailing_unique/i18n/es.po
odoo/addons/mass_mailing_unique/i18n/fr.po
odoo/addons/mass_mailing_unique/i18n/hr.po
odoo/addons/mass_mailing_unique/i18n/it.po
odoo/addons/mass_mailing_unique/i18n/mass_mailing_unique.pot
odoo/addons/mass_mailing_unique/i18n/pt.po
odoo/addons/mass_mailing_unique/i18n/sl.po
odoo/addons/mass_mailing_unique/models/__init__.py
odoo/addons/mass_mailing_unique/models/mailing_contact.py
odoo/addons/mass_mailing_unique/models/mailing_list.py
odoo/addons/mass_mailing_unique/readme/CONTRIBUTORS.rst
odoo/addons/mass_mailing_unique/readme/DESCRIPTION.rst
odoo/addons/mass_mailing_unique/readme/INSTALL.rst
odoo/addons/mass_mailing_unique/static/description/icon.png
odoo/addons/mass_mailing_unique/static/description/index.html
odoo/addons/mass_mailing_unique/tests/__init__.py
odoo/addons/mass_mailing_unique/tests/test_mass_mailing_unique.py
odoo14_addon_mass_mailing_unique-14.0.1.0.1.dev8.dist-info/METADATA
odoo14_addon_mass_mailing_unique-14.0.1.0.1.dev8.dist-info/WHEEL
odoo14_addon_mass_mailing_unique-14.0.1.0.1.dev8.dist-info/top_level.txt
odoo14_addon_mass_mailing_unique-14.0.1.0.1.dev8.dist-info/RECORD
